[
  {
    "__type__": "cc.SpriteFrame",
    "content": {
      "name": "恭喜获得",
      "texture": "15cb6e430",
      "rect": [
        2,
        90,
        535,
        150
      ],
      "offset": [
        0,
        -11
      ],
      "originalSize": [
        535,
        172
      ],
      "capInsets": [
        0,
        0,
        0,
        0
      ]
    }
  },
  [
    {
      "__type__": "cc.Prefab",
      "_name": "walfareWin",
      "data": {
        "__id__": 1
      }
    },
    {
      "__type__": "cc.Node",
      "_name": "walfare",
      "_children": [
        {
          "__id__": 2
        },
        {
          "__id__": 7
        },
        {
          "__id__": 8
        },
        {
          "__id__": 10
        }
      ],
      "_level": 1,
      "_components": [
        {
          "__type__": "cc.Sprite",
          "node": {
            "__id__": 1
          }
        },
        {
          "__type__": "e33afaNsF1JOLe5fwk4wzR/",
          "node": {
            "__id__": 1
          },
          "item": {
            "__uuid__": "f5A19+2fpIcIte44yEB6Ql"
          },
          "content": {
            "__id__": 10
          }
        },
        {
          "__type__": "cc.Widget",
          "node": {
            "__id__": 1
          },
          "_alignFlags": 45,
          "_originalWidth": 720,
          "_originalHeight": 1280
        }
      ],
      "_prefab": {
        "__type__": "cc.PrefabInfo",
        "root": {
          "__id__": 1
        },
        "asset": {
          "__uuid__": "7fCnDcaZVJPJs0JlURq0np"
        },
        "fileId": "07TX8bKwBIvJ/ezuIaDDC4"
      },
      "_contentSize": {
        "__type__": "cc.Size",
        "width": 720,
        "height": 1280
      },
      "_position": {
        "__type__": "cc.Vec3",
        "x": 360,
        "y": 640
      },
      "_scale": {
        "__type__": "cc.Vec3",
        "x": 1,
        "y": 1,
        "z": 1
      }
    },
    {
      "__type__": "cc.Node",
      "_name": "alert",
      "_parent": {
        "__id__": 1
      },
      "_children": [
        {
          "__id__": 3
        },
        {
          "__id__": 4
        },
        {
          "__id__": 5
        },
        {
          "__id__": 6
        }
      ],
      "_level": 2,
      "_components": [
        {
          "__type__": "72545s/zDBJDZf/21lBYqW2",
          "node": {
            "__id__": 2
          }
        },
        {
          "__type__": "cc.Widget",
          "node": {
            "__id__": 2
          },
          "_target": {
            "__id__": 1
          },
          "_alignFlags": 45,
          "_originalWidth": 40,
          "_originalHeight": 36
        }
      ],
      "_prefab": {
        "__type__": "cc.PrefabInfo",
        "root": {
          "__id__": 1
        },
        "asset": {
          "__uuid__": "7fCnDcaZVJPJs0JlURq0np"
        },
        "fileId": "31k01wl9RJJqRqOD0yv+nY"
      },
      "_contentSize": {
        "__type__": "cc.Size",
        "width": 720,
        "height": 1280
      },
      "_scale": {
        "__type__": "cc.Vec3",
        "x": 1,
        "y": 1,
        "z": 1
      }
    },
    {
      "__type__": "cc.Node",
      "_name": "black",
      "_parent": {
        "__id__": 2
      },
      "_level": 2,
      "_components": [
        {
          "__type__": "cc.Sprite",
          "node": {
            "__id__": 3
          },
          "_spriteFrame": {
            "__uuid__": "9fPZH/aV1B152L1wsy675S"
          },
          "_type": 1,
          "_sizeMode": 0
        },
        {
          "__type__": "cc.Widget",
          "node": {
            "__id__": 3
          },
          "_alignFlags": 45,
          "_originalWidth": 36,
          "_originalHeight": 34
        },
        {
          "__type__": "cc.Button",
          "node": {
            "__id__": 3
          },
          "clickEvents": [
            {
              "__type__": "cc.ClickEvent",
              "target": {
                "__id__": 2
              },
              "component": "Alert",
              "handler": "onBlackClick"
            }
          ],
          "_N$target": {
            "__id__": 3
          }
        }
      ],
      "_prefab": {
        "__type__": "cc.PrefabInfo",
        "root": {
          "__id__": 1
        },
        "asset": {
          "__uuid__": "7fCnDcaZVJPJs0JlURq0np"
        },
        "fileId": "dd+vDvxedL6ZprAo82JzV7"
      },
      "_opacity": 196,
      "_contentSize": {
        "__type__": "cc.Size",
        "width": 720,
        "height": 1280
      },
      "_scale": {
        "__type__": "cc.Vec3",
        "x": 1,
        "y": 1,
        "z": 1
      }
    },
    {
      "__type__": "cc.Node",
      "_name": "windowBg",
      "_parent": {
        "__id__": 2
      },
      "_active": false,
      "_level": 2,
      "_components": [
        {
          "__type__": "cc.Sprite",
          "node": {
            "__id__": 4
          },
          "_spriteFrame": {
            "__uuid__": "caqgMeWYZDELGs7iaTibOf"
          },
          "_type": 1,
          "_sizeMode": 0
        }
      ],
      "_prefab": {
        "__type__": "cc.PrefabInfo",
        "root": {
          "__id__": 1
        },
        "asset": {
          "__uuid__": "7fCnDcaZVJPJs0JlURq0np"
        },
        "fileId": "05rebM0P1BcIW3R+DFW3vz"
      },
      "_contentSize": {
        "__type__": "cc.Size",
        "width": 630,
        "height": 490
      },
      "_scale": {
        "__type__": "cc.Vec3",
        "x": 1,
        "y": 1,
        "z": 1
      }
    },
    {
      "__type__": "cc.Node",
      "_name": "windowTitle",
      "_parent": {
        "__id__": 2
      },
      "_active": false,
      "_level": 2,
      "_components": [
        {
          "__type__": "cc.Sprite",
          "node": {
            "__id__": 5
          },
          "_spriteFrame": {
            "__uuid__": "98lsNIDHZIRpILNI2WjULc"
          }
        }
      ],
      "_prefab": {
        "__type__": "cc.PrefabInfo",
        "root": {
          "__id__": 1
        },
        "asset": {
          "__uuid__": "7fCnDcaZVJPJs0JlURq0np"
        },
        "fileId": "d82+4AgTNDs6j1CJYeC540"
      },
      "_contentSize": {
        "__type__": "cc.Size",
        "width": 539,
        "height": 84
      },
      "_position": {
        "__type__": "cc.Vec3",
        "y": 240
      },
      "_scale": {
        "__type__": "cc.Vec3",
        "x": 1,
        "y": 1,
        "z": 1
      }
    },
    {
      "__type__": "cc.Node",
      "_name": "titleLabel",
      "_parent": {
        "__id__": 2
      },
      "_level": 2,
      "_components": [
        {
          "__type__": "cc.Label",
          "node": {
            "__id__": 6
          },
          "_srcBlendFactor": 1,
          "_useOriginalSize": false,
          "_string": "欢迎回来",
          "_N$string": "欢迎回来",
          "_N$horizontalAlign": 1,
          "_N$verticalAlign": 1,
          "_N$overflow": 1
        },
        {
          "__type__": "cc.LabelOutline",
          "node": {
            "__id__": 6
          },
          "_color": {
            "__type__": "cc.Color",
            "r": 2,
            "g": 150,
            "b": 2
          }
        }
      ],
      "_prefab": {
        "__type__": "cc.PrefabInfo",
        "root": {
          "__id__": 1
        },
        "asset": {
          "__uuid__": "7fCnDcaZVJPJs0JlURq0np"
        },
        "fileId": "bb7F1rnyNBg5qM+HpdF8z2"
      },
      "_contentSize": {
        "__type__": "cc.Size",
        "width": 300,
        "height": 43
      },
      "_position": {
        "__type__": "cc.Vec3",
        "y": 255
      },
      "_scale": {
        "__type__": "cc.Vec3",
        "x": 1,
        "y": 1,
        "z": 1
      }
    },
    {
      "__type__": "cc.Node",
      "_name": "恭喜获得",
      "_parent": {
        "__id__": 1
      },
      "_level": 2,
      "_components": [
        {
          "__type__": "cc.Sprite",
          "node": {
            "__id__": 7
          },
          "_spriteFrame": {
            "__uuid__": "75YRYy2fpKFLt4RAgey4ii"
          }
        }
      ],
      "_prefab": {
        "__type__": "cc.PrefabInfo",
        "root": {
          "__id__": 1
        },
        "asset": {
          "__uuid__": "7fCnDcaZVJPJs0JlURq0np"
        },
        "fileId": "74557YLQVN/66NDl7EAP0I"
      },
      "_contentSize": {
        "__type__": "cc.Size",
        "width": 535,
        "height": 150
      },
      "_position": {
        "__type__": "cc.Vec3",
        "y": 272
      },
      "_scale": {
        "__type__": "cc.Vec3",
        "x": 1,
        "y": 1,
        "z": 1
      }
    },
    {
      "__type__": "cc.Node",
      "_name": "btnYellow",
      "_parent": {
        "__id__": 1
      },
      "_children": [
        {
          "__id__": 9
        }
      ],
      "_level": 2,
      "_components": [
        {
          "__type__": "cc.Sprite",
          "node": {
            "__id__": 8
          },
          "_spriteFrame": {
            "__uuid__": "81OPK4OgJG8rUYcnnroMge"
          }
        },
        {
          "__type__": "cc.Button",
          "node": {
            "__id__": 8
          },
          "clickEvents": [
            {
              "__type__": "cc.ClickEvent",
              "target": {
                "__id__": 1
              },
              "component": "WalfareWin",
              "handler": "onClick"
            }
          ],
          "_N$target": {
            "__id__": 8
          }
        }
      ],
      "_prefab": {
        "__type__": "cc.PrefabInfo",
        "root": {
          "__id__": 1
        },
        "asset": {
          "__uuid__": "7fCnDcaZVJPJs0JlURq0np"
        },
        "fileId": "c6fi0PQ+VIYoKJ5tdNOU5c"
      },
      "_contentSize": {
        "__type__": "cc.Size",
        "width": 235,
        "height": 86
      },
      "_position": {
        "__type__": "cc.Vec3",
        "y": -313
      },
      "_scale": {
        "__type__": "cc.Vec3",
        "x": 1,
        "y": 1,
        "z": 1
      }
    },
    {
      "__type__": "cc.Node",
      "_name": "label",
      "_parent": {
        "__id__": 8
      },
      "_level": 3,
      "_components": [
        {
          "__type__": "cc.Label",
          "node": {
            "__id__": 9
          },
          "_srcBlendFactor": 1,
          "_useOriginalSize": false,
          "_string": "继续",
          "_N$string": "继续",
          "_fontSize": 50,
          "_lineHeight": 60,
          "_N$horizontalAlign": 1,
          "_N$verticalAlign": 1
        }
      ],
      "_prefab": {
        "__type__": "cc.PrefabInfo",
        "root": {
          "__id__": 1
        },
        "asset": {
          "__uuid__": "7fCnDcaZVJPJs0JlURq0np"
        },
        "fileId": "7606+ACOVBzIVUbXxeui5v"
      },
      "_color": {
        "__type__": "cc.Color",
        "r": 100,
        "g": 35,
        "b": 35
      },
      "_contentSize": {
        "__type__": "cc.Size",
        "width": 100,
        "height": 60
      },
      "_scale": {
        "__type__": "cc.Vec3",
        "x": 1,
        "y": 1,
        "z": 1
      }
    },
    {
      "__type__": "cc.Node",
      "_name": "content",
      "_parent": {
        "__id__": 1
      },
      "_level": 2,
      "_components": [
        {
          "__type__": "cc.Layout",
          "node": {
            "__id__": 10
          },
          "_layoutSize": {
            "__type__": "cc.Size",
            "width": 500,
            "height": 300
          },
          "_resize": 1,
          "_N$layoutType": 1,
          "_N$spacingX": 10
        }
      ],
      "_prefab": {
        "__type__": "cc.PrefabInfo",
        "root": {
          "__id__": 1
        },
        "asset": {
          "__uuid__": "7fCnDcaZVJPJs0JlURq0np"
        },
        "fileId": "efFMul6s9KIJmF92Tab7SF"
      },
      "_contentSize": {
        "__type__": "cc.Size",
        "width": 500,
        "height": 300
      },
      "_scale": {
        "__type__": "cc.Vec3",
        "x": 1,
        "y": 1,
        "z": 1
      }
    }
  ],
  {
    "__type__": "cc.SpriteFrame",
    "content": {
      "name": "btnYellow",
      "texture": "15cb6e430",
      "rect": [
        784,
        2,
        235,
        86
      ],
      "offset": [
        0,
        0
      ],
      "originalSize": [
        235,
        86
      ],
      "capInsets": [
        0,
        0,
        0,
        0
      ]
    }
  },
  {
    "__type__": "cc.SpriteFrame",
    "content": {
      "name": "windowTitle",
      "texture": "15cb6e430",
      "rect": [
        2,
        2,
        539,
        84
      ],
      "offset": [
        -0.5,
        1
      ],
      "originalSize": [
        544,
        90
      ],
      "capInsets": [
        0,
        0,
        0,
        0
      ]
    }
  },
  {
    "__type__": "cc.SpriteFrame",
    "content": {
      "name": "windowBg",
      "texture": "15cb6e430",
      "rect": [
        779,
        172,
        170,
        170
      ],
      "offset": [
        0,
        0
      ],
      "originalSize": [
        170,
        170
      ],
      "capInsets": [
        49,
        52,
        59,
        52
      ]
    }
  }
]